EasYoloD/__init__.py
EasYoloD/easyolo.py
easyolod-0.1.7.dist-info/METADATA
easyolod-0.1.7.dist-info/WHEEL
easyolod-0.1.7.dist-info/top_level.txt
easyolod-0.1.7.dist-info/RECORD
