Metadata-Version: 2.4
Name: EasYoloD
Version: 0.1.7
Summary: easyolo python library
Home-page: https://github.com/zaixia108/easyolo
Author: zaixia108
Author-email: xvbowen2012@gmail.com
License: MIT
Project-URL: Bug Tracker, https://github.com/zaixia108/easyolo/issues
Project-URL: Documentation, https://github.com/zaixia108/easyolo/wiki
Project-URL: Source Code, https://github.com/zaixia108/easyolo
Keywords: yolo,object detection,computer vision
Classifier: Development Status :: 3 - Alpha
Classifier: Intended Audience :: Developers
Classifier: License :: OSI Approved :: MIT License
Classifier: Programming Language :: Python :: 3
Classifier: Programming Language :: Python :: 3.8
Classifier: Programming Language :: Python :: 3.9
Classifier: Programming Language :: Python :: 3.10
Classifier: Programming Language :: Python :: 3.11
Classifier: Programming Language :: Python :: 3.12
Classifier: Operating System :: OS Independent
Requires-Python: >=3.8, <3.13
Requires-Dist: opencv-python<=4.10.0.84
Requires-Dist: numpy<=1.26
Dynamic: author
Dynamic: author-email
Dynamic: classifier
Dynamic: description
Dynamic: description-content-type
Dynamic: home-page
Dynamic: keywords
Dynamic: license
Dynamic: project-url
Dynamic: requires-dist
Dynamic: requires-python
Dynamic: summary
